tap_lever
