Metadata-Version: 1.1
Name: tap-lever
Version: 0.4.1
Summary: Singer.io tap for extracting data from the Lever API
Home-page: http://fishtownanalytics.com
Author: Fishtown Analytics
Author-email: UNKNOWN
License: UNKNOWN
Platform: UNKNOWN
Classifier: Programming Language :: Python :: 3 :: Only
